powercicd/__init__.py
powercicd/cli.py
powercicd/config.py
powercicd/config_utils.py
powercicd/json_utils.py
powercicd/powerapps/__init__.py
powercicd/powerapps/config.py
powercicd/powerbi/__init__.py
powercicd/powerbi/config.py
powercicd/powerbi/file_utils.py
powercicd/powerbi/powerbi_client.py
powercicd/powerbi/powerbi_utils.py
powercicd/shared/__init__.py
powercicd/shared/config.py
powercicd/shared/logging_utils.py
powercicd/shared/selenium_common.py
powercicd/sharepoint/__init__.py
powercicd/sharepoint/config.py
powercicd-1.0.24.dist-info/LICENSE
powercicd-1.0.24.dist-info/METADATA
powercicd-1.0.24.dist-info/WHEEL
powercicd-1.0.24.dist-info/entry_points.txt
powercicd-1.0.24.dist-info/top_level.txt
powercicd-1.0.24.dist-info/RECORD
