Metadata-Version: 2.1
Name: powercicd
Version: 1.0.24
Summary: Utility to automate the CI/CD process for Power Platform projects
Home-page: https://github.com/jeromerg/powercicd
Author: jeromerg
Author-email: jeromerg@gmx.net
Classifier: Programming Language :: Python :: 3
Classifier: License :: OSI Approved :: MIT License
Classifier: Operating System :: OS Independent
Requires-Python: >=3.10
License-File: LICENSE
Requires-Dist: aiohttp
Requires-Dist: azure-identity
Requires-Dist: coverage
Requires-Dist: jsonpath-ng
Requires-Dist: nest-asyncio
Requires-Dist: pydantic
Requires-Dist: python-dotenv
Requires-Dist: pyyaml
Requires-Dist: requests
Requires-Dist: selenium
Requires-Dist: tabulate
Requires-Dist: tenacity
Requires-Dist: typer[all]
Requires-Dist: wcmatch
